{
	"name": "Acrizia",
	"key": "l10n:hero-type/name?id=4720#static",
	"id": 4726,
	"avatar": "4720",
	"affinity": "Void",
	"hp": "15855",
	"atk": "1476",
	"def": "1046",
	"spd": "97",
	"res": "40",
	"acc": "0",
	"crate": "15",
	"cdamage": "63",
	"cheal": "50",
	"faction": "Dwarves",
	"aura": "Increase Ally C. RATE in  by 19",
	"totalBooks": "12",
	"skills": [
		{
			"desc": "Attacks 1 enemy. Has a 45% chance of placing a 60% [Decrease DEF] debuff for 2 turns. \r\n\r\nThe damage of this skill increases by 10% every time this skill is used. Stacks up to 100%.",
			"basedOn": "[ownersAscendLevel][||OwnerHasEffectOfKind][BlockPassiveSkills_KindId][Enemy MAX HP][HP][ATK][OwnerHasEffectOfKind]",
			"name": "Unflagging Assault",
			"maxcd": "0",
			"mincd": "0",
			"books": "Lvl. 2 Damage +5%\nLvl. 3 Buff/Debuff Chance +5%\nLvl. 4 Damage +10%\nLvl. 5 Buff/Debuff Chance +10%\n",
			"multiplier": "((ownersAscendLevel<3||OwnerHasEffectOfKind(BlockPassiveSkills_KindId))*(TRG_HP>=(2*HP))*2.5*ATK)+((TRG_HP<(2*HP))*2.5*ATK)+(!OwnerHasEffectOfKind(BlockPassiveSkills_KindId)*(ownersAscendLevel>=3)*(TRG_HP>=(2*HP))*0.02*TRG_HP)",
			"numBooksToMax": "4"
		},
		{
			"desc": "Attacks all enemies 2 times. Places a [Shield] buff on this Champion for 2 turns. The value of the [Shield] buff is equal to 5% of this Champion’s MAX HP for each critical hit.",
			"basedOn": "[ownersAscendLevel][||OwnerHasEffectOfKind][BlockPassiveSkills_KindId][Enemy MAX HP][HP][ATK][OwnerHasEffectOfKind]",
			"name": "Battlefield Domination",
			"maxcd": "4",
			"mincd": "3",
			"books": "Lvl. 2 Damage +5%\nLvl. 3 Damage +5%\nLvl. 4 Damage +10%\nLvl. 5 Cooldown -1\n",
			"multiplier": "((ownersAscendLevel<3||OwnerHasEffectOfKind(BlockPassiveSkills_KindId))*(TRG_HP>=(2*HP))*2*ATK)+((TRG_HP<(2*HP))*2*ATK)+(!OwnerHasEffectOfKind(BlockPassiveSkills_KindId)*(ownersAscendLevel>=3)*(TRG_HP>=(2*HP))*0.05*TRG_HP)",
			"numBooksToMax": "4"
		},
		{
			"desc": "Attacks 1 enemy 2 times. Has an 80% chance of stealing 100% of the target’s Turn Meter before attacking. This effect cannot be resisted if the target has higher MAX HP than this Champion.",
			"basedOn": "",
			"name": "Shut Down",
			"maxcd": "4",
			"mincd": "3",
			"books": "Lvl. 2 Buff/Debuff Chance +10%\nLvl. 3 Damage +10%\nLvl. 4 Buff/Debuff Chance +10%\nLvl. 5 Cooldown -1\n",
			"multiplier": "MAX_STAMINA",
			"numBooksToMax": "4"
		},
		{
			"desc": "Decreases the damage taken from AoE attacks by 50%. \r\n\r\nIf a target’s MAX HP is more than double this Champion's MAX HP, this Champion’s attacks will deal damage based on the target's MAX HP, instead of this Champion's ATK.",
			"basedOn": "",
			"name": "Grandeur [P]",
			"maxcd": "0",
			"mincd": "0",
			"books": "",
			"multiplier": "",
			"numBooksToMax": "0"
		}
	],
	"rarity": "Legendary",
	"type": "Attack"
}