{
	"key": "l10n:hero-type/name?id=800#static",
	"name": "Conquerer",
	"id": 806,
	"acc": "0",
	"affinity": "Spirit",
	"atk": "1421",
	"cdamage": "57",
	"crate": "15",
	"spd": "99",
	"def": "793",
	"hp": "12225",
	"cheal": "50",
	"res": "30",
	"faction": "Banner Lords",
	"rarity": "Rare",
	"type": "Attack",
	"aura": "Increases Ally ATK in All Battles by 18%.",
	"totalBooks": "14",
	"skills": [
		{
			"desc": "Attacks 1 enemy 2 times.",
			"basedOn": "[ATK]",
			"name": "Swift Blow",
			"maxcd": "0",
			"mincd": "0",
			"books": "Level 2: Damage +5%\nLevel 3: Damage +5%\nLevel 4: Damage +5%\nLevel 5: Damage +5%\n",
			"multiplier": "1.9*ATK",
			"numBooksToMax": "4"
		},
		{
			"desc": "Attacks 1 enemy. Removes 2 random buffs from the target.",
			"basedOn": "[ATK]",
			"name": "Cut Down To Size",
			"maxcd": "4",
			"mincd": "2",
			"books": "Level 2: Damage +5%\nLevel 3: Damage +5%\nLevel 4: Cooldown -1\nLevel 5: Cooldown -1\n",
			"multiplier": "5.2*ATK",
			"numBooksToMax": "4"
		},
		{
			"desc": "Attacks 1 enemy. Enemies killed by this skill cannot be revived.",
			"basedOn": "[ATK]",
			"name": "Purge",
			"maxcd": "5",
			"mincd": "3",
			"books": "Level 2: Damage +5%\nLevel 3: Damage +5%\nLevel 4: Cooldown -1\nLevel 5: Damage +0\nLevel 6: Damage +0\nLevel 7: Cooldown -1\n",
			"multiplier": "5.6*ATK",
			"numBooksToMax": "6"
		}
	]
}