{
	"name": "Brute",
	"id": 706,
	"avatar": "700",
	"hp": 14535,
	"atk": 1079,
	"def": 705,
	"spd": 92,
	"res": 30,
	"acc": 0,
	"crate": 15,
	"cdamage": 50,
	"cheal": 50,
	"faction": "Ogryn Tribes",
	"type": "",
	"totalBooks": "9",
	"skills": [
		{
			"desc": "Attacks 2 times at random. Has a 50% chance of placing a 5% [Poison] debuff for 1 turn if this attack is critical.",
			"basedOn": "[ATK]",
			"name": "Dirty Cuts",
			"maxcd": 0,
			"mincd": 0,
			"books": "Lvl. 2 Damage +5%\nLvl. 3 Damage +5%\nLvl. 4 Damage +5%\nLvl. 5 Damage +5%\n",
			"multiplier": "1.9*ATK",
			"numBooksToMax": 4
		},
		{
			"desc": "Attacks 1 enemy. Has an extra 30% chance of inflicting a critical hit.",
			"basedOn": "[ATK]",
			"name": "Rip and Tear",
			"maxcd": 3,
			"mincd": 2,
			"books": "Lvl. 2 Damage +5%\nLvl. 3 Damage +5%\nLvl. 4 Damage +5%\nLvl. 5 Damage +5%\n",
			"multiplier": "6*ATK",
			"numBooksToMax": 5
		}
	]
}