{
	"name": "Jinglehunter",
	"id": 3026,
	"avatar": "3020",
	"hp": 14700,
	"atk": 1498,
	"def": 826,
	"spd": 101,
	"res": 30,
	"acc": 0,
	"crate": 15,
	"cdamage": 60,
	"cheal": 50,
	"faction": "High Elves",
	"type": "Increase Ally SPD in Arena battles by 24",
	"totalBooks": "14",
	"skills": [
		{
			"desc": "Attacks 1 enemy 2 times. Has a 40% chance of placing a 30% [Decrease SPD] debuff for 2 turns if this attack is critical.",
			"basedOn": "[ATK]",
			"name": "Missile Toe",
			"maxcd": 0,
			"mincd": 0,
			"books": "Lvl. 2 Damage +5%\nLvl. 3 Buff/Debuff Chance +5%\nLvl. 4 Damage +5%\nLvl. 5 Buff/Debuff Chance +5%\nLvl. 6 Damage +10%\n",
			"multiplier": "1.7*ATK",
			"numBooksToMax": 5
		},
		{
			"desc": "Attacks 1 enemy. Has a 90% chance of placing a [Freeze] debuff on all enemies for 1 turn if this attack kills the enemy.",
			"basedOn": "[ATK]",
			"name": "Jacked Frost",
			"maxcd": 4,
			"mincd": 3,
			"books": "Lvl. 2 Damage +5%\nLvl. 3 Buff/Debuff Chance +5%\nLvl. 4 Damage +5%\nLvl. 5 Buff/Debuff Chance +5%\n",
			"multiplier": "5.9*ATK",
			"numBooksToMax": 5
		},
		{
			"desc": "Attacks all enemies. Decreases the Turn Meter by 20% if this attack is critical. Fills this Champion's Turn Meter by 10% if this attack is critical.",
			"basedOn": "[ATK]",
			"name": "Cold Snap",
			"maxcd": 5,
			"mincd": 4,
			"books": "Lvl. 2 Damage +5%\nLvl. 3 Damage +5%\nLvl. 4 Damage +10%\n",
			"multiplier": "3.8*ATK",
			"numBooksToMax": 4
		}
	]
}